{
    "client": "Thunder Client",
    "collectionName": "SecretFriend - Node",
    "dateExported": "2023-12-09T01:51:28.489Z",
    "version": "1.1",
    "folders": [
        {
            "_id": "a642cbd0-622c-4ce4-b9c6-0b81de20e37c",
            "name": "Admin Routes",
            "containerId": "",
            "created": "2023-12-07T20:43:44.831Z",
            "sortNum": 10000
        },
        {
            "_id": "d013b30f-4ef1-4eca-97af-72ed08707b19",
            "name": "Admin Routes Copy",
            "containerId": "",
            "created": "2023-12-09T01:17:54.450Z",
            "sortNum": 10000
        },
        {
            "_id": "8f16d70f-96ad-4585-890e-f82455f55a59",
            "name": "Events",
            "containerId": "a642cbd0-622c-4ce4-b9c6-0b81de20e37c",
            "created": "2023-12-07T20:44:28.036Z",
            "sortNum": 20000
        },
        {
            "_id": "987fca2a-7862-4dbb-b37e-afbe13a5d1f5",
            "name": "Events",
            "containerId": "d013b30f-4ef1-4eca-97af-72ed08707b19",
            "created": "2023-12-09T01:17:54.451Z",
            "sortNum": 20000
        },
        {
            "_id": "7f6b064e-35ea-443b-8875-f00fcec6c61a",
            "name": "Groups",
            "containerId": "a642cbd0-622c-4ce4-b9c6-0b81de20e37c",
            "created": "2023-12-09T00:02:13.810Z",
            "sortNum": 30000
        },
        {
            "_id": "d0bd8133-04b9-483d-98db-d450da13a997",
            "name": "Groups",
            "containerId": "d013b30f-4ef1-4eca-97af-72ed08707b19",
            "created": "2023-12-09T01:17:54.452Z",
            "sortNum": 30000
        }
    ],
    "requests": [
        {
            "_id": "05ea3d0b-3cea-45d5-8f71-7bf2bae7dffe",
            "colId": "518d75ec-cf15-4b91-ae1c-64e778c47e20",
            "containerId": "",
            "name": "Ping",
            "url": "{{base}}/ping",
            "method": "GET",
            "sortNum": 10000,
            "created": "2023-12-05T22:43:40.024Z",
            "modified": "2023-12-06T20:50:10.008Z",
            "headers": [],
            "params": [],
            "tests": []
        },
        {
            "_id": "8e72da14-bc68-436d-811f-c521e9dd416a",
            "colId": "518d75ec-cf15-4b91-ae1c-64e778c47e20",
            "containerId": "a642cbd0-622c-4ce4-b9c6-0b81de20e37c",
            "name": "Ping Admin",
            "url": "{{base}}/admin/ping",
            "method": "GET",
            "sortNum": 10000,
            "created": "2023-12-06T21:47:06.711Z",
            "modified": "2023-12-07T20:17:50.928Z",
            "headers": [
                {
                    "name": "Accept",
                    "value": "*/*",
                    "isDisabled": true
                },
                {
                    "name": "User-Agent",
                    "value": "Thunder Client (https://www.thunderclient.com)",
                    "isDisabled": true
                },
                {
                    "name": "Authorization",
                    "value": "Token 56415214840307122023"
                }
            ],
            "params": [],
            "tests": []
        },
        {
            "_id": "fad6ad4f-97f0-4144-a0e1-f469468f9eae",
            "colId": "518d75ec-cf15-4b91-ae1c-64e778c47e20",
            "containerId": "8f16d70f-96ad-4585-890e-f82455f55a59",
            "name": "Events",
            "url": "{{base}}/admin/events",
            "method": "GET",
            "sortNum": 10000,
            "created": "2023-12-07T20:15:33.478Z",
            "modified": "2023-12-07T20:19:02.945Z",
            "headers": [
                {
                    "name": "Authorization",
                    "value": "Token 56415214840307122023"
                }
            ],
            "params": [],
            "tests": []
        },
        {
            "_id": "abfb6aaa-8ef1-48e2-90bf-dea23b819771",
            "colId": "518d75ec-cf15-4b91-ae1c-64e778c47e20",
            "containerId": "7f6b064e-35ea-443b-8875-f00fcec6c61a",
            "name": "Groups",
            "url": "{{base}}/admin/events/1/groups",
            "method": "GET",
            "sortNum": 10000,
            "created": "2023-12-09T00:02:18.386Z",
            "modified": "2023-12-09T00:11:38.717Z",
            "headers": [
                {
                    "name": "Authorization",
                    "value": "Token 56415214840308122023"
                }
            ],
            "params": [],
            "tests": []
        },
        {
            "_id": "164f008f-7164-414c-aa0b-08b6d9f76a35",
            "colId": "518d75ec-cf15-4b91-ae1c-64e778c47e20",
            "containerId": "d013b30f-4ef1-4eca-97af-72ed08707b19",
            "name": "Ping Admin",
            "url": "{{base}}/admin/ping",
            "method": "GET",
            "sortNum": 10000,
            "created": "2023-12-09T01:17:54.450Z",
            "modified": "2023-12-09T01:17:54.450Z",
            "headers": [
                {
                    "name": "Accept",
                    "value": "*/*",
                    "isDisabled": true
                },
                {
                    "name": "User-Agent",
                    "value": "Thunder Client (https://www.thunderclient.com)",
                    "isDisabled": true
                },
                {
                    "name": "Authorization",
                    "value": "Token 56415214840307122023"
                }
            ],
            "params": [],
            "tests": []
        },
        {
            "_id": "5462792a-0bb5-442f-a1dc-62365a33d217",
            "colId": "518d75ec-cf15-4b91-ae1c-64e778c47e20",
            "containerId": "987fca2a-7862-4dbb-b37e-afbe13a5d1f5",
            "name": "Events",
            "url": "{{base}}/admin/events",
            "method": "GET",
            "sortNum": 10000,
            "created": "2023-12-09T01:17:54.452Z",
            "modified": "2023-12-09T01:17:54.450Z",
            "headers": [
                {
                    "name": "Authorization",
                    "value": "Token 56415214840307122023"
                }
            ],
            "params": [],
            "tests": []
        },
        {
            "_id": "a24383e2-f9cc-4df0-bff9-c9e41c8984b3",
            "colId": "518d75ec-cf15-4b91-ae1c-64e778c47e20",
            "containerId": "d0bd8133-04b9-483d-98db-d450da13a997",
            "name": "Groups",
            "url": "{{base}}/admin/events/1/groups",
            "method": "GET",
            "sortNum": 10000,
            "created": "2023-12-09T01:17:54.457Z",
            "modified": "2023-12-09T01:17:54.450Z",
            "headers": [
                {
                    "name": "Authorization",
                    "value": "Token 56415214840308122023"
                }
            ],
            "params": [],
            "tests": []
        },
        {
            "_id": "712537eb-dfe8-4dbc-b76e-dacae8d82802",
            "colId": "518d75ec-cf15-4b91-ae1c-64e778c47e20",
            "containerId": "8f16d70f-96ad-4585-890e-f82455f55a59",
            "name": "Event by Id",
            "url": "{{base}}/admin/events/1",
            "method": "GET",
            "sortNum": 20000,
            "created": "2023-12-07T20:40:43.596Z",
            "modified": "2023-12-07T20:41:22.834Z",
            "headers": [
                {
                    "name": "Authorization",
                    "value": "Token 56415214840307122023"
                }
            ],
            "params": [],
            "tests": []
        },
        {
            "_id": "078c3a3a-2fba-47d1-8444-89f5e9cbb176",
            "colId": "518d75ec-cf15-4b91-ae1c-64e778c47e20",
            "containerId": "7f6b064e-35ea-443b-8875-f00fcec6c61a",
            "name": "Group by Id",
            "url": "{{base}}/admin/events/1/groups/1",
            "method": "GET",
            "sortNum": 20000,
            "created": "2023-12-09T01:14:51.407Z",
            "modified": "2023-12-09T01:16:43.671Z",
            "headers": [
                {
                    "name": "Authorization",
                    "value": "Token 56415214840308122023"
                }
            ],
            "params": [],
            "tests": []
        },
        {
            "_id": "f9d74a0b-e6e2-4a5c-b376-16724bf887e6",
            "colId": "518d75ec-cf15-4b91-ae1c-64e778c47e20",
            "containerId": "987fca2a-7862-4dbb-b37e-afbe13a5d1f5",
            "name": "Event by Id",
            "url": "{{base}}/admin/events/1",
            "method": "GET",
            "sortNum": 20000,
            "created": "2023-12-09T01:17:54.453Z",
            "modified": "2023-12-09T01:17:54.450Z",
            "headers": [
                {
                    "name": "Authorization",
                    "value": "Token 56415214840307122023"
                }
            ],
            "params": [],
            "tests": []
        },
        {
            "_id": "60cf2298-38e5-426f-86ff-e9c92191a937",
            "colId": "518d75ec-cf15-4b91-ae1c-64e778c47e20",
            "containerId": "d0bd8133-04b9-483d-98db-d450da13a997",
            "name": "Group by Id",
            "url": "{{base}}/admin/events/1/groups/1",
            "method": "GET",
            "sortNum": 20000,
            "created": "2023-12-09T01:17:54.458Z",
            "modified": "2023-12-09T01:17:54.450Z",
            "headers": [
                {
                    "name": "Authorization",
                    "value": "Token 56415214840308122023"
                }
            ],
            "params": [],
            "tests": []
        },
        {
            "_id": "3ed68781-26e8-44be-a196-55632b724810",
            "colId": "518d75ec-cf15-4b91-ae1c-64e778c47e20",
            "containerId": "8f16d70f-96ad-4585-890e-f82455f55a59",
            "name": "New Event",
            "url": "{{base}}/admin/events",
            "method": "POST",
            "sortNum": 30000,
            "created": "2023-12-07T21:21:30.085Z",
            "modified": "2023-12-07T21:48:03.534Z",
            "headers": [
                {
                    "name": "Authorization",
                    "value": "Token 56415214840307122023"
                }
            ],
            "params": [],
            "body": {
                "type": "json",
                "raw": "{\n  \"title\": \"Test4\",\n  \"description\": \"Test4\",\n  \"grouped\": false\n}",
                "form": []
            },
            "tests": []
        },
        {
            "_id": "c2528c99-d7cf-46cb-ac45-801353cc2a15",
            "colId": "518d75ec-cf15-4b91-ae1c-64e778c47e20",
            "containerId": "987fca2a-7862-4dbb-b37e-afbe13a5d1f5",
            "name": "New Event",
            "url": "{{base}}/admin/events",
            "method": "POST",
            "sortNum": 30000,
            "created": "2023-12-09T01:17:54.454Z",
            "modified": "2023-12-09T01:17:54.450Z",
            "headers": [
                {
                    "name": "Authorization",
                    "value": "Token 56415214840307122023"
                }
            ],
            "params": [],
            "body": {
                "type": "json",
                "raw": "{\n  \"title\": \"Test4\",\n  \"description\": \"Test4\",\n  \"grouped\": false\n}",
                "form": []
            },
            "tests": []
        },
        {
            "_id": "39b96941-c48d-403c-b1e5-17c4ab3ea088",
            "colId": "518d75ec-cf15-4b91-ae1c-64e778c47e20",
            "containerId": "7f6b064e-35ea-443b-8875-f00fcec6c61a",
            "name": "New Group",
            "url": "{{base}}/admin/events/1/groups",
            "method": "POST",
            "sortNum": 30000,
            "created": "2023-12-09T01:49:37.907Z",
            "modified": "2023-12-09T01:50:54.522Z",
            "headers": [
                {
                    "name": "Authorization",
                    "value": "Token 56415214840308122023"
                }
            ],
            "params": [],
            "body": {
                "type": "json",
                "raw": "{\n  \"name\": \"Test\"\n}",
                "form": []
            },
            "tests": []
        },
        {
            "_id": "cdcde599-af7f-4e59-ad9f-362ffeb54987",
            "colId": "518d75ec-cf15-4b91-ae1c-64e778c47e20",
            "containerId": "a642cbd0-622c-4ce4-b9c6-0b81de20e37c",
            "name": "Login",
            "url": "{{base}}/admin/login",
            "method": "POST",
            "sortNum": 40000,
            "created": "2023-12-06T20:50:51.629Z",
            "modified": "2023-12-07T20:17:40.415Z",
            "headers": [],
            "params": [],
            "body": {
                "type": "json",
                "raw": "{\n  \"password\": \"07122023\"\n}",
                "form": []
            },
            "tests": []
        },
        {
            "_id": "d09fca82-11d4-437d-82a7-d28196437da0",
            "colId": "518d75ec-cf15-4b91-ae1c-64e778c47e20",
            "containerId": "8f16d70f-96ad-4585-890e-f82455f55a59",
            "name": "Update Event",
            "url": "{{base}}/admin/events/2",
            "method": "PUT",
            "sortNum": 40000,
            "created": "2023-12-07T21:37:59.468Z",
            "modified": "2023-12-07T21:38:38.119Z",
            "headers": [
                {
                    "name": "Authorization",
                    "value": "Token 56415214840307122023"
                }
            ],
            "params": [],
            "body": {
                "type": "json",
                "raw": "{\n  \"title\": \"Test2 - Edit\",\n  \"description\": \"Test2\",\n  \"grouped\": true\n}",
                "form": []
            },
            "tests": []
        },
        {
            "_id": "61b0e11c-b74c-43fd-bfc5-c4150248b168",
            "colId": "518d75ec-cf15-4b91-ae1c-64e778c47e20",
            "containerId": "d013b30f-4ef1-4eca-97af-72ed08707b19",
            "name": "Login",
            "url": "{{base}}/admin/login",
            "method": "POST",
            "sortNum": 40000,
            "created": "2023-12-09T01:17:54.451Z",
            "modified": "2023-12-09T01:17:54.450Z",
            "headers": [],
            "params": [],
            "body": {
                "type": "json",
                "raw": "{\n  \"password\": \"07122023\"\n}",
                "form": []
            },
            "tests": []
        },
        {
            "_id": "7bbeccd5-90e3-4676-8cc9-2ef1890e6e42",
            "colId": "518d75ec-cf15-4b91-ae1c-64e778c47e20",
            "containerId": "987fca2a-7862-4dbb-b37e-afbe13a5d1f5",
            "name": "Update Event",
            "url": "{{base}}/admin/events/2",
            "method": "PUT",
            "sortNum": 40000,
            "created": "2023-12-09T01:17:54.455Z",
            "modified": "2023-12-09T01:17:54.450Z",
            "headers": [
                {
                    "name": "Authorization",
                    "value": "Token 56415214840307122023"
                }
            ],
            "params": [],
            "body": {
                "type": "json",
                "raw": "{\n  \"title\": \"Test2 - Edit\",\n  \"description\": \"Test2\",\n  \"grouped\": true\n}",
                "form": []
            },
            "tests": []
        },
        {
            "_id": "ce0f6615-98b4-459e-85a6-059b9816c30e",
            "colId": "518d75ec-cf15-4b91-ae1c-64e778c47e20",
            "containerId": "8f16d70f-96ad-4585-890e-f82455f55a59",
            "name": "Delete Event",
            "url": "{{base}}/admin/events/3",
            "method": "DELETE",
            "sortNum": 50000,
            "created": "2023-12-07T21:46:58.825Z",
            "modified": "2023-12-07T21:51:26.635Z",
            "headers": [
                {
                    "name": "Authorization",
                    "value": "Token 56415214840307122023"
                }
            ],
            "params": [],
            "tests": []
        },
        {
            "_id": "1f3a47aa-13ce-4b41-83b4-e59a7cad9d98",
            "colId": "518d75ec-cf15-4b91-ae1c-64e778c47e20",
            "containerId": "987fca2a-7862-4dbb-b37e-afbe13a5d1f5",
            "name": "Delete Event",
            "url": "{{base}}/admin/events/3",
            "method": "DELETE",
            "sortNum": 50000,
            "created": "2023-12-09T01:17:54.456Z",
            "modified": "2023-12-09T01:17:54.450Z",
            "headers": [
                {
                    "name": "Authorization",
                    "value": "Token 56415214840307122023"
                }
            ],
            "params": [],
            "tests": []
        }
    ]
}